{
  "type": "pfm:furniture",
  "group": "kitchen",
  "ingredients": [
    {
      "item": "alexscaves:pewen_planks"
    },
    {
      "item": "alexscaves:pewen_planks"
    },
    {
      "item": "alexscaves:pewen_planks"
    },
    {
      "item": "alexscaves:pewen_planks"
    },
    {
      "item": "alexscaves:pewen_planks"
    },
    {
      "item": "alexscaves:pewen_planks"
    },
    {
      "item": "alexscaves:pewen_log"
    },
    {
      "item": "alexscaves:pewen_log"
    },
    {
      "item": "alexscaves:pewen_log"
    }
  ],
  "result": {
    "count": 6,
    "item": "pfm:pewen_alexscaves_kitchen_counter"
  }
}